Metadata-Version: 1.1
Name: keyagent
Version: 0.1
Summary: KeyChest agent for local monitoring of keys and certificates - keystore scanning on the host and local networks
Home-page: http://keychest.net
Author: Radical Prime Limited
Author-email: support@radicalprime.com
License: MIT License
